OutputFileTester/ProgramTester.py
OutputFileTester/__init__.py
uarizona_ece275_outputfileTester-0.0.20.dist-info/LICENSE
uarizona_ece275_outputfileTester-0.0.20.dist-info/METADATA
uarizona_ece275_outputfileTester-0.0.20.dist-info/WHEEL
uarizona_ece275_outputfileTester-0.0.20.dist-info/top_level.txt
uarizona_ece275_outputfileTester-0.0.20.dist-info/RECORD
