Metadata-Version: 2.1
Name: uarizona-ece275-outputfileTester
Version: 0.0.20
Summary: Packaage used to test and compare output files for ECE 275 @ the University of Arizona
Home-page: https://github.com/connorfuhrman/OutputFileTester
Author: Connor Fuhrman
Author-email: connorfuhrman@email.arizona.edu
License: UNKNOWN
Platform: UNKNOWN
Classifier: Programming Language :: Python :: 3
Classifier: License :: OSI Approved :: MIT License
Classifier: Operating System :: OS Independent
Requires-Python: >=3.6
